{
  "manifest": {
    "kind": "directive.crewDataset",
    "schemaVersion": 1,
    "id": "eudora-vale.senior-staff",
    "packageId": "directive:campaign-package:eudora-vale-broken-accord",
    "title": "U.S.S. Eudora Vale Senior Staff",
    "version": "0.1.0-pre-alpha.1",
    "status": "draft"
  },
  "sources": [
    {
      "title": "Eudora Vale Senior Staff Character Bible",
      "path": "content/campaigns/eudora-vale/crew/EUDORA_VALE_SENIOR_STAFF_CHARACTER_BIBLE.md"
    },
    {
      "title": "Crew Dataset Contract",
      "path": "docs/packages/CREW_DATASET_CONTRACT.md"
    }
  ],
  "officers": [
    {
      "id": "nasrin-rhee",
      "name": "Nasrin Rhee",
      "billet": "Commanding Officer",
      "requiredCardTypes": [
        "crew.profile",
        "crew.voice",
        "crew.relationship",
        "crew.development"
      ]
    },
    {
      "id": "asha-ren",
      "name": "Asha Ren",
      "billet": "Operations Chief and Second Officer; prospective Acting Executive Officer",
      "requiredCardTypes": [
        "crew.profile",
        "crew.voice",
        "crew.relationship",
        "crew.development"
      ]
    },
    {
      "id": "haro-chveth",
      "name": "Haro ch'Veth",
      "billet": "Chief Science Officer and Climatologist",
      "requiredCardTypes": [
        "crew.profile",
        "crew.voice",
        "crew.relationship",
        "crew.development"
      ]
    },
    {
      "id": "milo-fenn",
      "name": "Milo Fenn",
      "billet": "Chief Engineer",
      "requiredCardTypes": [
        "crew.profile",
        "crew.voice",
        "crew.relationship",
        "crew.development"
      ]
    },
    {
      "id": "ila-tovan",
      "name": "Ila Tovan",
      "billet": "Chief Medical Officer and Public-Health Specialist",
      "requiredCardTypes": [
        "crew.profile",
        "crew.voice",
        "crew.relationship",
        "crew.development"
      ]
    },
    {
      "id": "koris-zhraal",
      "name": "Koris zh'Raal",
      "billet": "Chief Tactical and Security Officer",
      "requiredCardTypes": [
        "crew.profile",
        "crew.voice",
        "crew.relationship",
        "crew.development"
      ]
    },
    {
      "id": "jaya-kel",
      "name": "Jaya Kel",
      "billet": "Chief Flight Control Officer",
      "requiredCardTypes": [
        "crew.profile",
        "crew.voice",
        "crew.relationship",
        "crew.development"
      ]
    },
    {
      "id": "venn-talar",
      "name": "Venn Talar",
      "billet": "Counselor and Diplomatic Support Officer",
      "requiredCardTypes": [
        "crew.profile",
        "crew.voice",
        "crew.relationship",
        "crew.development"
      ]
    }
  ],
  "relationshipDimensions": [
    {
      "id": "professionalConfidence",
      "title": "ProfessionalConfidence",
      "visibility": "hidden",
      "summary": "Hidden relationship dimension tracked by the crew Director."
    },
    {
      "id": "integrityTrust",
      "title": "IntegrityTrust",
      "visibility": "hidden",
      "summary": "Hidden relationship dimension tracked by the crew Director."
    },
    {
      "id": "personalRapport",
      "title": "PersonalRapport",
      "visibility": "hidden",
      "summary": "Hidden relationship dimension tracked by the crew Director."
    }
  ],
  "developmentDimensions": [
    {
      "id": "operationalExperience",
      "title": "Operational Experience",
      "visibility": "hidden",
      "summary": "Operational Experience is tracked as Director-only crew development state."
    },
    {
      "id": "playerMentorship",
      "title": "Player Mentorship",
      "visibility": "hidden",
      "summary": "Player Mentorship is tracked as Director-only crew development state."
    },
    {
      "id": "personalArcProgress",
      "title": "Personal Arc Progress",
      "visibility": "hidden",
      "summary": "Personal Arc Progress is tracked as Director-only crew development state."
    },
    {
      "id": "commandConfidence",
      "title": "Command Confidence",
      "visibility": "hidden",
      "summary": "Command Confidence is tracked as Director-only crew development state."
    },
    {
      "id": "professionalStrain",
      "title": "Professional Strain",
      "visibility": "hidden",
      "summary": "Professional Strain is tracked as Director-only crew development state."
    }
  ],
  "cards": [
    {
      "id": "crew.nasrin-rhee.profile",
      "type": "crew.profile",
      "title": "Nasrin Rhee service-record profile",
      "datasetId": "eudora-vale.senior-staff",
      "source": {
        "document": "content/campaigns/eudora-vale/crew/EUDORA_VALE_SENIOR_STAFF_CHARACTER_BIBLE.md",
        "refs": []
      },
      "visibility": "publicPackage",
      "audiences": [
        "crewDirector",
        "missionDirector",
        "narrator"
      ],
      "scope": {
        "characters": [
          "nasrin-rhee"
        ],
        "missions": [
          "prelude-the-captains-chair"
        ],
        "campaigns": [
          "broken-accord"
        ],
        "stardateFrom": 55291.4
      },
      "gates": {
        "playerKnowledge": "serviceRecord",
        "relationshipMin": null,
        "developmentMin": null,
        "requiresRevealedFactIds": [],
        "blocksUntilFactIds": [],
        "requiresOutcomeIds": []
      },
      "retrieval": {
        "lanes": [
          "crew_profile",
          "command"
        ],
        "keywords": [
          "Nasrin Rhee",
          "Commanding Officer",
          "Human"
        ],
        "priority": "high"
      },
      "payload": {
        "summary": "A respected, cautious captain who treats negotiated access and technical patience as command tools. She leads the opening shuttle evacuation and is killed after its passengers transport clear.",
        "constraints": [
          "Use as player-safe crew context; do not write for the player."
        ],
        "narratorSafe": true,
        "stateRefs": [
          "crew.nasrin-rhee"
        ],
        "effects": []
      }
    },
    {
      "id": "crew.nasrin-rhee.voice",
      "type": "crew.voice",
      "title": "Nasrin Rhee voice and conduct",
      "datasetId": "eudora-vale.senior-staff",
      "source": {
        "document": "content/campaigns/eudora-vale/crew/EUDORA_VALE_SENIOR_STAFF_CHARACTER_BIBLE.md",
        "refs": []
      },
      "visibility": "playerDiscoverable",
      "audiences": [
        "crewDirector",
        "missionDirector",
        "narrator"
      ],
      "scope": {
        "characters": [
          "nasrin-rhee"
        ],
        "missions": [
          "prelude-the-captains-chair"
        ],
        "campaigns": [
          "broken-accord"
        ],
        "stardateFrom": 55291.4
      },
      "gates": {
        "playerKnowledge": "professionalConversation",
        "relationshipMin": null,
        "developmentMin": null,
        "requiresRevealedFactIds": [],
        "blocksUntilFactIds": [],
        "requiresOutcomeIds": []
      },
      "retrieval": {
        "lanes": [
          "crew_voice",
          "dialogue"
        ],
        "keywords": [
          "Nasrin Rhee",
          "voice",
          "command"
        ],
        "priority": "normal"
      },
      "payload": {
        "summary": "Measured, economical, and attentive to who must live with a decision after the ship leaves. Rhee asks what can be defended publicly and what cannot yet be known.",
        "constraints": [
          "Keep dialogue consistent with the officer bible and never make the player speak."
        ],
        "narratorSafe": true,
        "stateRefs": [
          "crew.nasrin-rhee"
        ],
        "effects": []
      }
    },
    {
      "id": "crew.nasrin-rhee.relationship",
      "type": "crew.relationship",
      "title": "Nasrin Rhee relationship pressures",
      "datasetId": "eudora-vale.senior-staff",
      "source": {
        "document": "content/campaigns/eudora-vale/crew/EUDORA_VALE_SENIOR_STAFF_CHARACTER_BIBLE.md",
        "refs": []
      },
      "visibility": "directorOnly",
      "audiences": [
        "crewDirector",
        "missionDirector"
      ],
      "scope": {
        "characters": [
          "nasrin-rhee"
        ],
        "missions": [
          "prelude-the-captains-chair"
        ],
        "campaigns": [
          "broken-accord"
        ],
        "stardateFrom": 55291.4
      },
      "gates": {
        "playerKnowledge": "highTrust",
        "relationshipMin": null,
        "developmentMin": null,
        "requiresRevealedFactIds": [],
        "blocksUntilFactIds": [],
        "requiresOutcomeIds": []
      },
      "retrieval": {
        "lanes": [
          "crew_relationship",
          "pressure"
        ],
        "keywords": [
          "Nasrin Rhee",
          "relationship",
          "trust"
        ],
        "priority": "normal"
      },
      "payload": {
        "summary": "ProfessionalConfidence: Credible in role; the player's first independent captaincy has not yet been tested. IntegrityTrust: Begins with Starfleet professional trust and changes through candor, accountability, and treatment of hidden costs. PersonalRapport: Familiar from prior XO service, but transformed by the succession and Rhee's death.",
        "constraints": [
          "Relationship values are hidden; show behavior, not numbers."
        ],
        "narratorSafe": false,
        "stateRefs": [
          "relationships.nasrin-rhee"
        ],
        "effects": []
      }
    },
    {
      "id": "crew.nasrin-rhee.development",
      "type": "crew.development",
      "title": "Nasrin Rhee development hooks",
      "datasetId": "eudora-vale.senior-staff",
      "source": {
        "document": "content/campaigns/eudora-vale/crew/EUDORA_VALE_SENIOR_STAFF_CHARACTER_BIBLE.md",
        "refs": []
      },
      "visibility": "directorOnly",
      "audiences": [
        "crewDirector",
        "missionDirector"
      ],
      "scope": {
        "characters": [
          "nasrin-rhee"
        ],
        "missions": [
          "prelude-the-captains-chair"
        ],
        "campaigns": [
          "broken-accord"
        ],
        "stardateFrom": 55291.4
      },
      "gates": {
        "playerKnowledge": "crisisDisclosure",
        "relationshipMin": null,
        "developmentMin": null,
        "requiresRevealedFactIds": [],
        "blocksUntilFactIds": [],
        "requiresOutcomeIds": []
      },
      "retrieval": {
        "lanes": [
          "crew_development",
          "bplot"
        ],
        "keywords": [
          "Nasrin Rhee",
          "development",
          "legacy",
          "command-privacy",
          "accountability",
          "unfinished-policy"
        ],
        "priority": "normal"
      },
      "payload": {
        "summary": "legacy, command-privacy, accountability, unfinished-policy | The crew invokes her precedent Her logs complicate disclosure Her death makes ordinary captaincy rituals politically charged",
        "constraints": [
          "Use as Director-only arc material until revealed in play."
        ],
        "narratorSafe": false,
        "stateRefs": [
          "crew.nasrin-rhee.development"
        ],
        "effects": []
      }
    },
    {
      "id": "crew.asha-ren.profile",
      "type": "crew.profile",
      "title": "Asha Ren service-record profile",
      "datasetId": "eudora-vale.senior-staff",
      "source": {
        "document": "content/campaigns/eudora-vale/crew/EUDORA_VALE_SENIOR_STAFF_CHARACTER_BIBLE.md",
        "refs": []
      },
      "visibility": "publicPackage",
      "audiences": [
        "crewDirector",
        "missionDirector",
        "narrator"
      ],
      "scope": {
        "characters": [
          "asha-ren"
        ],
        "missions": [
          "prelude-the-captains-chair"
        ],
        "campaigns": [
          "broken-accord"
        ],
        "stardateFrom": 55291.4
      },
      "gates": {
        "playerKnowledge": "serviceRecord",
        "relationshipMin": null,
        "developmentMin": null,
        "requiresRevealedFactIds": [],
        "blocksUntilFactIds": [],
        "requiresOutcomeIds": []
      },
      "retrieval": {
        "lanes": [
          "crew_profile",
          "command"
        ],
        "keywords": [
          "Asha Ren",
          "Operations Chief and Second Officer; prospective Acting Executive Officer",
          "Bajoran"
        ],
        "priority": "normal"
      },
      "payload": {
        "summary": "Organized, direct, and politically perceptive. Ren understands how operational schedules become power and is the strongest default candidate to become Acting XO.",
        "constraints": [
          "Use as player-safe crew context; do not write for the player."
        ],
        "narratorSafe": true,
        "stateRefs": [
          "crew.asha-ren"
        ],
        "effects": []
      }
    },
    {
      "id": "crew.asha-ren.voice",
      "type": "crew.voice",
      "title": "Asha Ren voice and conduct",
      "datasetId": "eudora-vale.senior-staff",
      "source": {
        "document": "content/campaigns/eudora-vale/crew/EUDORA_VALE_SENIOR_STAFF_CHARACTER_BIBLE.md",
        "refs": []
      },
      "visibility": "playerDiscoverable",
      "audiences": [
        "crewDirector",
        "missionDirector",
        "narrator"
      ],
      "scope": {
        "characters": [
          "asha-ren"
        ],
        "missions": [
          "prelude-the-captains-chair"
        ],
        "campaigns": [
          "broken-accord"
        ],
        "stardateFrom": 55291.4
      },
      "gates": {
        "playerKnowledge": "professionalConversation",
        "relationshipMin": null,
        "developmentMin": null,
        "requiresRevealedFactIds": [],
        "blocksUntilFactIds": [],
        "requiresOutcomeIds": []
      },
      "retrieval": {
        "lanes": [
          "crew_voice",
          "dialogue"
        ],
        "keywords": [
          "Asha Ren",
          "voice",
          "operations"
        ],
        "priority": "normal"
      },
      "payload": {
        "summary": "Clear, compressed, and unsentimental about institutional language. Ren identifies who owns a process, who is excluded, and what decision is being disguised as administration.",
        "constraints": [
          "Keep dialogue consistent with the officer bible and never make the player speak."
        ],
        "narratorSafe": true,
        "stateRefs": [
          "crew.asha-ren"
        ],
        "effects": []
      }
    },
    {
      "id": "crew.asha-ren.relationship",
      "type": "crew.relationship",
      "title": "Asha Ren relationship pressures",
      "datasetId": "eudora-vale.senior-staff",
      "source": {
        "document": "content/campaigns/eudora-vale/crew/EUDORA_VALE_SENIOR_STAFF_CHARACTER_BIBLE.md",
        "refs": []
      },
      "visibility": "directorOnly",
      "audiences": [
        "crewDirector",
        "missionDirector"
      ],
      "scope": {
        "characters": [
          "asha-ren"
        ],
        "missions": [
          "prelude-the-captains-chair"
        ],
        "campaigns": [
          "broken-accord"
        ],
        "stardateFrom": 55291.4
      },
      "gates": {
        "playerKnowledge": "highTrust",
        "relationshipMin": null,
        "developmentMin": null,
        "requiresRevealedFactIds": [],
        "blocksUntilFactIds": [],
        "requiresOutcomeIds": []
      },
      "retrieval": {
        "lanes": [
          "crew_relationship",
          "pressure"
        ],
        "keywords": [
          "Asha Ren",
          "relationship",
          "trust"
        ],
        "priority": "normal"
      },
      "payload": {
        "summary": "ProfessionalConfidence: Credible in role; the player's first independent captaincy has not yet been tested. IntegrityTrust: Begins with Starfleet professional trust and changes through candor, accountability, and treatment of hidden costs. PersonalRapport: Familiar from prior XO service, but transformed by the succession and Rhee's death.",
        "constraints": [
          "Relationship values are hidden; show behavior, not numbers."
        ],
        "narratorSafe": false,
        "stateRefs": [
          "relationships.asha-ren"
        ],
        "effects": []
      }
    },
    {
      "id": "crew.asha-ren.development",
      "type": "crew.development",
      "title": "Asha Ren development hooks",
      "datasetId": "eudora-vale.senior-staff",
      "source": {
        "document": "content/campaigns/eudora-vale/crew/EUDORA_VALE_SENIOR_STAFF_CHARACTER_BIBLE.md",
        "refs": []
      },
      "visibility": "directorOnly",
      "audiences": [
        "crewDirector",
        "missionDirector"
      ],
      "scope": {
        "characters": [
          "asha-ren"
        ],
        "missions": [
          "prelude-the-captains-chair"
        ],
        "campaigns": [
          "broken-accord"
        ],
        "stardateFrom": 55291.4
      },
      "gates": {
        "playerKnowledge": "crisisDisclosure",
        "relationshipMin": null,
        "developmentMin": null,
        "requiresRevealedFactIds": [],
        "blocksUntilFactIds": [],
        "requiresOutcomeIds": []
      },
      "retrieval": {
        "lanes": [
          "crew_development",
          "bplot"
        ],
        "keywords": [
          "Asha Ren",
          "development",
          "executive-authority",
          "delegation",
          "political-reading",
          "loyal-dissent"
        ],
        "priority": "normal"
      },
      "payload": {
        "summary": "executive-authority, delegation, political-reading, loyal-dissent | Must run the ship while the player governs the system Challenges informal commitments that lack implementation May decline or redefine the acting XO role",
        "constraints": [
          "Use as Director-only arc material until revealed in play."
        ],
        "narratorSafe": false,
        "stateRefs": [
          "crew.asha-ren.development"
        ],
        "effects": []
      }
    },
    {
      "id": "crew.haro-chveth.profile",
      "type": "crew.profile",
      "title": "Haro ch'Veth service-record profile",
      "datasetId": "eudora-vale.senior-staff",
      "source": {
        "document": "content/campaigns/eudora-vale/crew/EUDORA_VALE_SENIOR_STAFF_CHARACTER_BIBLE.md",
        "refs": []
      },
      "visibility": "publicPackage",
      "audiences": [
        "crewDirector",
        "missionDirector",
        "narrator"
      ],
      "scope": {
        "characters": [
          "haro-chveth"
        ],
        "missions": [
          "prelude-the-captains-chair"
        ],
        "campaigns": [
          "broken-accord"
        ],
        "stardateFrom": 55291.4
      },
      "gates": {
        "playerKnowledge": "serviceRecord",
        "relationshipMin": null,
        "developmentMin": null,
        "requiresRevealedFactIds": [],
        "blocksUntilFactIds": [],
        "requiresOutcomeIds": []
      },
      "retrieval": {
        "lanes": [
          "crew_profile",
          "command"
        ],
        "keywords": [
          "Haro ch'Veth",
          "Chief Science Officer and Climatologist",
          "Andorian"
        ],
        "priority": "normal"
      },
      "payload": {
        "summary": "Energetic, empirical, and impatient with ceremonial assurances. He can model the lattice at system scale but dislikes treating uncertainty as political permission to conceal data.",
        "constraints": [
          "Use as player-safe crew context; do not write for the player."
        ],
        "narratorSafe": true,
        "stateRefs": [
          "crew.haro-chveth"
        ],
        "effects": []
      }
    },
    {
      "id": "crew.haro-chveth.voice",
      "type": "crew.voice",
      "title": "Haro ch'Veth voice and conduct",
      "datasetId": "eudora-vale.senior-staff",
      "source": {
        "document": "content/campaigns/eudora-vale/crew/EUDORA_VALE_SENIOR_STAFF_CHARACTER_BIBLE.md",
        "refs": []
      },
      "visibility": "playerDiscoverable",
      "audiences": [
        "crewDirector",
        "missionDirector",
        "narrator"
      ],
      "scope": {
        "characters": [
          "haro-chveth"
        ],
        "missions": [
          "prelude-the-captains-chair"
        ],
        "campaigns": [
          "broken-accord"
        ],
        "stardateFrom": 55291.4
      },
      "gates": {
        "playerKnowledge": "professionalConversation",
        "relationshipMin": null,
        "developmentMin": null,
        "requiresRevealedFactIds": [],
        "blocksUntilFactIds": [],
        "requiresOutcomeIds": []
      },
      "retrieval": {
        "lanes": [
          "crew_voice",
          "dialogue"
        ],
        "keywords": [
          "Haro ch'Veth",
          "voice",
          "science"
        ],
        "priority": "normal"
      },
      "payload": {
        "summary": "Fast, precise, and openly skeptical. ch'Veth separates measurements from policy and states confidence levels even when the room wants certainty.",
        "constraints": [
          "Keep dialogue consistent with the officer bible and never make the player speak."
        ],
        "narratorSafe": true,
        "stateRefs": [
          "crew.haro-chveth"
        ],
        "effects": []
      }
    },
    {
      "id": "crew.haro-chveth.relationship",
      "type": "crew.relationship",
      "title": "Haro ch'Veth relationship pressures",
      "datasetId": "eudora-vale.senior-staff",
      "source": {
        "document": "content/campaigns/eudora-vale/crew/EUDORA_VALE_SENIOR_STAFF_CHARACTER_BIBLE.md",
        "refs": []
      },
      "visibility": "directorOnly",
      "audiences": [
        "crewDirector",
        "missionDirector"
      ],
      "scope": {
        "characters": [
          "haro-chveth"
        ],
        "missions": [
          "prelude-the-captains-chair"
        ],
        "campaigns": [
          "broken-accord"
        ],
        "stardateFrom": 55291.4
      },
      "gates": {
        "playerKnowledge": "highTrust",
        "relationshipMin": null,
        "developmentMin": null,
        "requiresRevealedFactIds": [],
        "blocksUntilFactIds": [],
        "requiresOutcomeIds": []
      },
      "retrieval": {
        "lanes": [
          "crew_relationship",
          "pressure"
        ],
        "keywords": [
          "Haro ch'Veth",
          "relationship",
          "trust"
        ],
        "priority": "normal"
      },
      "payload": {
        "summary": "ProfessionalConfidence: Credible in role; the player's first independent captaincy has not yet been tested. IntegrityTrust: Begins with Starfleet professional trust and changes through candor, accountability, and treatment of hidden costs. PersonalRapport: Familiar from prior XO service, but transformed by the succession and Rhee's death.",
        "constraints": [
          "Relationship values are hidden; show behavior, not numbers."
        ],
        "narratorSafe": false,
        "stateRefs": [
          "relationships.haro-chveth"
        ],
        "effects": []
      }
    },
    {
      "id": "crew.haro-chveth.development",
      "type": "crew.development",
      "title": "Haro ch'Veth development hooks",
      "datasetId": "eudora-vale.senior-staff",
      "source": {
        "document": "content/campaigns/eudora-vale/crew/EUDORA_VALE_SENIOR_STAFF_CHARACTER_BIBLE.md",
        "refs": []
      },
      "visibility": "directorOnly",
      "audiences": [
        "crewDirector",
        "missionDirector"
      ],
      "scope": {
        "characters": [
          "haro-chveth"
        ],
        "missions": [
          "prelude-the-captains-chair"
        ],
        "campaigns": [
          "broken-accord"
        ],
        "stardateFrom": 55291.4
      },
      "gates": {
        "playerKnowledge": "crisisDisclosure",
        "relationshipMin": null,
        "developmentMin": null,
        "requiresRevealedFactIds": [],
        "blocksUntilFactIds": [],
        "requiresOutcomeIds": []
      },
      "retrieval": {
        "lanes": [
          "crew_development",
          "bplot"
        ],
        "keywords": [
          "Haro ch'Veth",
          "development",
          "scientific-candor",
          "transition-risk",
          "public-communication",
          "ecological-systems"
        ],
        "priority": "normal"
      },
      "payload": {
        "summary": "scientific-candor, transition-risk, public-communication, ecological-systems | Advocates broad telemetry access Disputes secrecy with Fenn and Osei Can overvalue elegant models",
        "constraints": [
          "Use as Director-only arc material until revealed in play."
        ],
        "narratorSafe": false,
        "stateRefs": [
          "crew.haro-chveth.development"
        ],
        "effects": []
      }
    },
    {
      "id": "crew.milo-fenn.profile",
      "type": "crew.profile",
      "title": "Milo Fenn service-record profile",
      "datasetId": "eudora-vale.senior-staff",
      "source": {
        "document": "content/campaigns/eudora-vale/crew/EUDORA_VALE_SENIOR_STAFF_CHARACTER_BIBLE.md",
        "refs": []
      },
      "visibility": "publicPackage",
      "audiences": [
        "crewDirector",
        "missionDirector",
        "narrator"
      ],
      "scope": {
        "characters": [
          "milo-fenn"
        ],
        "missions": [
          "prelude-the-captains-chair"
        ],
        "campaigns": [
          "broken-accord"
        ],
        "stardateFrom": 55291.4
      },
      "gates": {
        "playerKnowledge": "serviceRecord",
        "relationshipMin": null,
        "developmentMin": null,
        "requiresRevealedFactIds": [],
        "blocksUntilFactIds": [],
        "requiresOutcomeIds": []
      },
      "retrieval": {
        "lanes": [
          "crew_profile",
          "command"
        ],
        "keywords": [
          "Milo Fenn",
          "Chief Engineer",
          "Human"
        ],
        "priority": "normal"
      },
      "payload": {
        "summary": "An imaginative systems architect with a dry manner. Fenn sees the lattice as one machine distributed across five societies and is cautious about destabilizing it faster than alternatives can be built.",
        "constraints": [
          "Use as player-safe crew context; do not write for the player."
        ],
        "narratorSafe": true,
        "stateRefs": [
          "crew.milo-fenn"
        ],
        "effects": []
      }
    },
    {
      "id": "crew.milo-fenn.voice",
      "type": "crew.voice",
      "title": "Milo Fenn voice and conduct",
      "datasetId": "eudora-vale.senior-staff",
      "source": {
        "document": "content/campaigns/eudora-vale/crew/EUDORA_VALE_SENIOR_STAFF_CHARACTER_BIBLE.md",
        "refs": []
      },
      "visibility": "playerDiscoverable",
      "audiences": [
        "crewDirector",
        "missionDirector",
        "narrator"
      ],
      "scope": {
        "characters": [
          "milo-fenn"
        ],
        "missions": [
          "prelude-the-captains-chair"
        ],
        "campaigns": [
          "broken-accord"
        ],
        "stardateFrom": 55291.4
      },
      "gates": {
        "playerKnowledge": "professionalConversation",
        "relationshipMin": null,
        "developmentMin": null,
        "requiresRevealedFactIds": [],
        "blocksUntilFactIds": [],
        "requiresOutcomeIds": []
      },
      "retrieval": {
        "lanes": [
          "crew_voice",
          "dialogue"
        ],
        "keywords": [
          "Milo Fenn",
          "voice",
          "engineering"
        ],
        "priority": "normal"
      },
      "payload": {
        "summary": "Dry, concrete, and diagram-minded. Fenn turns policy into load paths, failure margins, fabrication hours, and the location where a promised compromise will physically break.",
        "constraints": [
          "Keep dialogue consistent with the officer bible and never make the player speak."
        ],
        "narratorSafe": true,
        "stateRefs": [
          "crew.milo-fenn"
        ],
        "effects": []
      }
    },
    {
      "id": "crew.milo-fenn.relationship",
      "type": "crew.relationship",
      "title": "Milo Fenn relationship pressures",
      "datasetId": "eudora-vale.senior-staff",
      "source": {
        "document": "content/campaigns/eudora-vale/crew/EUDORA_VALE_SENIOR_STAFF_CHARACTER_BIBLE.md",
        "refs": []
      },
      "visibility": "directorOnly",
      "audiences": [
        "crewDirector",
        "missionDirector"
      ],
      "scope": {
        "characters": [
          "milo-fenn"
        ],
        "missions": [
          "prelude-the-captains-chair"
        ],
        "campaigns": [
          "broken-accord"
        ],
        "stardateFrom": 55291.4
      },
      "gates": {
        "playerKnowledge": "highTrust",
        "relationshipMin": null,
        "developmentMin": null,
        "requiresRevealedFactIds": [],
        "blocksUntilFactIds": [],
        "requiresOutcomeIds": []
      },
      "retrieval": {
        "lanes": [
          "crew_relationship",
          "pressure"
        ],
        "keywords": [
          "Milo Fenn",
          "relationship",
          "trust"
        ],
        "priority": "normal"
      },
      "payload": {
        "summary": "ProfessionalConfidence: Credible in role; the player's first independent captaincy has not yet been tested. IntegrityTrust: Begins with Starfleet professional trust and changes through candor, accountability, and treatment of hidden costs. PersonalRapport: Familiar from prior XO service, but transformed by the succession and Rhee's death.",
        "constraints": [
          "Relationship values are hidden; show behavior, not numbers."
        ],
        "narratorSafe": false,
        "stateRefs": [
          "relationships.milo-fenn"
        ],
        "effects": []
      }
    },
    {
      "id": "crew.milo-fenn.development",
      "type": "crew.development",
      "title": "Milo Fenn development hooks",
      "datasetId": "eudora-vale.senior-staff",
      "source": {
        "document": "content/campaigns/eudora-vale/crew/EUDORA_VALE_SENIOR_STAFF_CHARACTER_BIBLE.md",
        "refs": []
      },
      "visibility": "directorOnly",
      "audiences": [
        "crewDirector",
        "missionDirector"
      ],
      "scope": {
        "characters": [
          "milo-fenn"
        ],
        "missions": [
          "prelude-the-captains-chair"
        ],
        "campaigns": [
          "broken-accord"
        ],
        "stardateFrom": 55291.4
      },
      "gates": {
        "playerKnowledge": "crisisDisclosure",
        "relationshipMin": null,
        "developmentMin": null,
        "requiresRevealedFactIds": [],
        "blocksUntilFactIds": [],
        "requiresOutcomeIds": []
      },
      "retrieval": {
        "lanes": [
          "crew_development",
          "bplot"
        ],
        "keywords": [
          "Milo Fenn",
          "development",
          "engineering-candor",
          "culpability",
          "repair-before-disclosure",
          "mentorship"
        ],
        "priority": "normal"
      },
      "payload": {
        "summary": "engineering-candor, culpability, repair-before-disclosure, mentorship | Needs scarce feedstock Argues for staged change Must decide whether to disclose his prior certification before others find it",
        "constraints": [
          "Use as Director-only arc material until revealed in play."
        ],
        "narratorSafe": false,
        "stateRefs": [
          "crew.milo-fenn.development"
        ],
        "effects": []
      }
    },
    {
      "id": "crew.ila-tovan.profile",
      "type": "crew.profile",
      "title": "Ila Tovan service-record profile",
      "datasetId": "eudora-vale.senior-staff",
      "source": {
        "document": "content/campaigns/eudora-vale/crew/EUDORA_VALE_SENIOR_STAFF_CHARACTER_BIBLE.md",
        "refs": []
      },
      "visibility": "publicPackage",
      "audiences": [
        "crewDirector",
        "missionDirector",
        "narrator"
      ],
      "scope": {
        "characters": [
          "ila-tovan"
        ],
        "missions": [
          "prelude-the-captains-chair"
        ],
        "campaigns": [
          "broken-accord"
        ],
        "stardateFrom": 55291.4
      },
      "gates": {
        "playerKnowledge": "serviceRecord",
        "relationshipMin": null,
        "developmentMin": null,
        "requiresRevealedFactIds": [],
        "blocksUntilFactIds": [],
        "requiresOutcomeIds": []
      },
      "retrieval": {
        "lanes": [
          "crew_profile",
          "command"
        ],
        "keywords": [
          "Ila Tovan",
          "Chief Medical Officer and Public-Health Specialist",
          "Trill"
        ],
        "priority": "normal"
      },
      "payload": {
        "summary": "Measured and attentive to population effects. Tovan treats environmental allocation as triage and resists technical language that hides who becomes sick, displaced, or infertile.",
        "constraints": [
          "Use as player-safe crew context; do not write for the player."
        ],
        "narratorSafe": true,
        "stateRefs": [
          "crew.ila-tovan"
        ],
        "effects": []
      }
    },
    {
      "id": "crew.ila-tovan.voice",
      "type": "crew.voice",
      "title": "Ila Tovan voice and conduct",
      "datasetId": "eudora-vale.senior-staff",
      "source": {
        "document": "content/campaigns/eudora-vale/crew/EUDORA_VALE_SENIOR_STAFF_CHARACTER_BIBLE.md",
        "refs": []
      },
      "visibility": "playerDiscoverable",
      "audiences": [
        "crewDirector",
        "missionDirector",
        "narrator"
      ],
      "scope": {
        "characters": [
          "ila-tovan"
        ],
        "missions": [
          "prelude-the-captains-chair"
        ],
        "campaigns": [
          "broken-accord"
        ],
        "stardateFrom": 55291.4
      },
      "gates": {
        "playerKnowledge": "professionalConversation",
        "relationshipMin": null,
        "developmentMin": null,
        "requiresRevealedFactIds": [],
        "blocksUntilFactIds": [],
        "requiresOutcomeIds": []
      },
      "retrieval": {
        "lanes": [
          "crew_voice",
          "dialogue"
        ],
        "keywords": [
          "Ila Tovan",
          "voice",
          "medical"
        ],
        "priority": "normal"
      },
      "payload": {
        "summary": "Quiet, exact, and difficult to deflect. Tovan distinguishes reversible discomfort, chronic harm, acute mortality, and political embarrassment.",
        "constraints": [
          "Keep dialogue consistent with the officer bible and never make the player speak."
        ],
        "narratorSafe": true,
        "stateRefs": [
          "crew.ila-tovan"
        ],
        "effects": []
      }
    },
    {
      "id": "crew.ila-tovan.relationship",
      "type": "crew.relationship",
      "title": "Ila Tovan relationship pressures",
      "datasetId": "eudora-vale.senior-staff",
      "source": {
        "document": "content/campaigns/eudora-vale/crew/EUDORA_VALE_SENIOR_STAFF_CHARACTER_BIBLE.md",
        "refs": []
      },
      "visibility": "directorOnly",
      "audiences": [
        "crewDirector",
        "missionDirector"
      ],
      "scope": {
        "characters": [
          "ila-tovan"
        ],
        "missions": [
          "prelude-the-captains-chair"
        ],
        "campaigns": [
          "broken-accord"
        ],
        "stardateFrom": 55291.4
      },
      "gates": {
        "playerKnowledge": "highTrust",
        "relationshipMin": null,
        "developmentMin": null,
        "requiresRevealedFactIds": [],
        "blocksUntilFactIds": [],
        "requiresOutcomeIds": []
      },
      "retrieval": {
        "lanes": [
          "crew_relationship",
          "pressure"
        ],
        "keywords": [
          "Ila Tovan",
          "relationship",
          "trust"
        ],
        "priority": "normal"
      },
      "payload": {
        "summary": "ProfessionalConfidence: Credible in role; the player's first independent captaincy has not yet been tested. IntegrityTrust: Begins with Starfleet professional trust and changes through candor, accountability, and treatment of hidden costs. PersonalRapport: Familiar from prior XO service, but transformed by the succession and Rhee's death.",
        "constraints": [
          "Relationship values are hidden; show behavior, not numbers."
        ],
        "narratorSafe": false,
        "stateRefs": [
          "relationships.ila-tovan"
        ],
        "effects": []
      }
    },
    {
      "id": "crew.ila-tovan.development",
      "type": "crew.development",
      "title": "Ila Tovan development hooks",
      "datasetId": "eudora-vale.senior-staff",
      "source": {
        "document": "content/campaigns/eudora-vale/crew/EUDORA_VALE_SENIOR_STAFF_CHARACTER_BIBLE.md",
        "refs": []
      },
      "visibility": "directorOnly",
      "audiences": [
        "crewDirector",
        "missionDirector"
      ],
      "scope": {
        "characters": [
          "ila-tovan"
        ],
        "missions": [
          "prelude-the-captains-chair"
        ],
        "campaigns": [
          "broken-accord"
        ],
        "stardateFrom": 55291.4
      },
      "gates": {
        "playerKnowledge": "crisisDisclosure",
        "relationshipMin": null,
        "developmentMin": null,
        "requiresRevealedFactIds": [],
        "blocksUntilFactIds": [],
        "requiresOutcomeIds": []
      },
      "retrieval": {
        "lanes": [
          "crew_development",
          "bplot"
        ],
        "keywords": [
          "Ila Tovan",
          "development",
          "population-triage",
          "medical-independence",
          "reparations",
          "consent"
        ],
        "priority": "normal"
      },
      "payload": {
        "summary": "population-triage, medical-independence, reparations, consent | Nacre registries are incomplete Medical supplies compete with processor parts Can refuse to certify a lethal allocation as safe",
        "constraints": [
          "Use as Director-only arc material until revealed in play."
        ],
        "narratorSafe": false,
        "stateRefs": [
          "crew.ila-tovan.development"
        ],
        "effects": []
      }
    },
    {
      "id": "crew.koris-zhraal.profile",
      "type": "crew.profile",
      "title": "Koris zh'Raal service-record profile",
      "datasetId": "eudora-vale.senior-staff",
      "source": {
        "document": "content/campaigns/eudora-vale/crew/EUDORA_VALE_SENIOR_STAFF_CHARACTER_BIBLE.md",
        "refs": []
      },
      "visibility": "publicPackage",
      "audiences": [
        "crewDirector",
        "missionDirector",
        "narrator"
      ],
      "scope": {
        "characters": [
          "koris-zhraal"
        ],
        "missions": [
          "prelude-the-captains-chair"
        ],
        "campaigns": [
          "broken-accord"
        ],
        "stardateFrom": 55291.4
      },
      "gates": {
        "playerKnowledge": "serviceRecord",
        "relationshipMin": null,
        "developmentMin": null,
        "requiresRevealedFactIds": [],
        "blocksUntilFactIds": [],
        "requiresOutcomeIds": []
      },
      "retrieval": {
        "lanes": [
          "crew_profile",
          "command"
        ],
        "keywords": [
          "Koris zh'Raal",
          "Chief Tactical and Security Officer",
          "Andorian"
        ],
        "priority": "normal"
      },
      "payload": {
        "summary": "Disciplined, restrained, and experienced in civil disorder. zh'Raal expects sabotage and coercion to increase but does not want the Eudora Vale used as an occupying police force.",
        "constraints": [
          "Use as player-safe crew context; do not write for the player."
        ],
        "narratorSafe": true,
        "stateRefs": [
          "crew.koris-zhraal"
        ],
        "effects": []
      }
    },
    {
      "id": "crew.koris-zhraal.voice",
      "type": "crew.voice",
      "title": "Koris zh'Raal voice and conduct",
      "datasetId": "eudora-vale.senior-staff",
      "source": {
        "document": "content/campaigns/eudora-vale/crew/EUDORA_VALE_SENIOR_STAFF_CHARACTER_BIBLE.md",
        "refs": []
      },
      "visibility": "playerDiscoverable",
      "audiences": [
        "crewDirector",
        "missionDirector",
        "narrator"
      ],
      "scope": {
        "characters": [
          "koris-zhraal"
        ],
        "missions": [
          "prelude-the-captains-chair"
        ],
        "campaigns": [
          "broken-accord"
        ],
        "stardateFrom": 55291.4
      },
      "gates": {
        "playerKnowledge": "professionalConversation",
        "relationshipMin": null,
        "developmentMin": null,
        "requiresRevealedFactIds": [],
        "blocksUntilFactIds": [],
        "requiresOutcomeIds": []
      },
      "retrieval": {
        "lanes": [
          "crew_voice",
          "dialogue"
        ],
        "keywords": [
          "Koris zh'Raal",
          "voice",
          "security"
        ],
        "priority": "normal"
      },
      "payload": {
        "summary": "Controlled, specific, and procedural. zh'Raal distinguishes a dangerous person, a dangerous crowd, and an authority trying to call dissent a security problem.",
        "constraints": [
          "Keep dialogue consistent with the officer bible and never make the player speak."
        ],
        "narratorSafe": true,
        "stateRefs": [
          "crew.koris-zhraal"
        ],
        "effects": []
      }
    },
    {
      "id": "crew.koris-zhraal.relationship",
      "type": "crew.relationship",
      "title": "Koris zh'Raal relationship pressures",
      "datasetId": "eudora-vale.senior-staff",
      "source": {
        "document": "content/campaigns/eudora-vale/crew/EUDORA_VALE_SENIOR_STAFF_CHARACTER_BIBLE.md",
        "refs": []
      },
      "visibility": "directorOnly",
      "audiences": [
        "crewDirector",
        "missionDirector"
      ],
      "scope": {
        "characters": [
          "koris-zhraal"
        ],
        "missions": [
          "prelude-the-captains-chair"
        ],
        "campaigns": [
          "broken-accord"
        ],
        "stardateFrom": 55291.4
      },
      "gates": {
        "playerKnowledge": "highTrust",
        "relationshipMin": null,
        "developmentMin": null,
        "requiresRevealedFactIds": [],
        "blocksUntilFactIds": [],
        "requiresOutcomeIds": []
      },
      "retrieval": {
        "lanes": [
          "crew_relationship",
          "pressure"
        ],
        "keywords": [
          "Koris zh'Raal",
          "relationship",
          "trust"
        ],
        "priority": "normal"
      },
      "payload": {
        "summary": "ProfessionalConfidence: Credible in role; the player's first independent captaincy has not yet been tested. IntegrityTrust: Begins with Starfleet professional trust and changes through candor, accountability, and treatment of hidden costs. PersonalRapport: Familiar from prior XO service, but transformed by the succession and Rhee's death.",
        "constraints": [
          "Relationship values are hidden; show behavior, not numbers."
        ],
        "narratorSafe": false,
        "stateRefs": [
          "relationships.koris-zhraal"
        ],
        "effects": []
      }
    },
    {
      "id": "crew.koris-zhraal.development",
      "type": "crew.development",
      "title": "Koris zh'Raal development hooks",
      "datasetId": "eudora-vale.senior-staff",
      "source": {
        "document": "content/campaigns/eudora-vale/crew/EUDORA_VALE_SENIOR_STAFF_CHARACTER_BIBLE.md",
        "refs": []
      },
      "visibility": "directorOnly",
      "audiences": [
        "crewDirector",
        "missionDirector"
      ],
      "scope": {
        "characters": [
          "koris-zhraal"
        ],
        "missions": [
          "prelude-the-captains-chair"
        ],
        "campaigns": [
          "broken-accord"
        ],
        "stardateFrom": 55291.4
      },
      "gates": {
        "playerKnowledge": "crisisDisclosure",
        "relationshipMin": null,
        "developmentMin": null,
        "requiresRevealedFactIds": [],
        "blocksUntilFactIds": [],
        "requiresOutcomeIds": []
      },
      "retrieval": {
        "lanes": [
          "crew_development",
          "bplot"
        ],
        "keywords": [
          "Koris zh'Raal",
          "development",
          "proportional-force",
          "civil-order",
          "local-partners",
          "evidence-security"
        ],
        "priority": "normal"
      },
      "payload": {
        "summary": "proportional-force, civil-order, local-partners, evidence-security | Node seizures blur sabotage and labor action Local security requests tactical backing Evidence custody can conflict with rescue",
        "constraints": [
          "Use as Director-only arc material until revealed in play."
        ],
        "narratorSafe": false,
        "stateRefs": [
          "crew.koris-zhraal.development"
        ],
        "effects": []
      }
    },
    {
      "id": "crew.jaya-kel.profile",
      "type": "crew.profile",
      "title": "Jaya Kel service-record profile",
      "datasetId": "eudora-vale.senior-staff",
      "source": {
        "document": "content/campaigns/eudora-vale/crew/EUDORA_VALE_SENIOR_STAFF_CHARACTER_BIBLE.md",
        "refs": []
      },
      "visibility": "publicPackage",
      "audiences": [
        "crewDirector",
        "missionDirector",
        "narrator"
      ],
      "scope": {
        "characters": [
          "jaya-kel"
        ],
        "missions": [
          "prelude-the-captains-chair"
        ],
        "campaigns": [
          "broken-accord"
        ],
        "stardateFrom": 55291.4
      },
      "gates": {
        "playerKnowledge": "serviceRecord",
        "relationshipMin": null,
        "developmentMin": null,
        "requiresRevealedFactIds": [],
        "blocksUntilFactIds": [],
        "requiresOutcomeIds": []
      },
      "retrieval": {
        "lanes": [
          "crew_profile",
          "command"
        ],
        "keywords": [
          "Jaya Kel",
          "Chief Flight Control Officer",
          "Human"
        ],
        "priority": "normal"
      },
      "payload": {
        "summary": "Calm, practical, and highly familiar with orbital traffic. Kel planned the shuttle corridor used in the opening evacuation and responds to Rhee's death by trying to control every variable.",
        "constraints": [
          "Use as player-safe crew context; do not write for the player."
        ],
        "narratorSafe": true,
        "stateRefs": [
          "crew.jaya-kel"
        ],
        "effects": []
      }
    },
    {
      "id": "crew.jaya-kel.voice",
      "type": "crew.voice",
      "title": "Jaya Kel voice and conduct",
      "datasetId": "eudora-vale.senior-staff",
      "source": {
        "document": "content/campaigns/eudora-vale/crew/EUDORA_VALE_SENIOR_STAFF_CHARACTER_BIBLE.md",
        "refs": []
      },
      "visibility": "playerDiscoverable",
      "audiences": [
        "crewDirector",
        "missionDirector",
        "narrator"
      ],
      "scope": {
        "characters": [
          "jaya-kel"
        ],
        "missions": [
          "prelude-the-captains-chair"
        ],
        "campaigns": [
          "broken-accord"
        ],
        "stardateFrom": 55291.4
      },
      "gates": {
        "playerKnowledge": "professionalConversation",
        "relationshipMin": null,
        "developmentMin": null,
        "requiresRevealedFactIds": [],
        "blocksUntilFactIds": [],
        "requiresOutcomeIds": []
      },
      "retrieval": {
        "lanes": [
          "crew_voice",
          "dialogue"
        ],
        "keywords": [
          "Jaya Kel",
          "voice",
          "flight"
        ],
        "priority": "normal"
      },
      "payload": {
        "summary": "Brief, spatial, and practical. Kel describes vectors, windows, traffic behavior, and the one assumption in a plan most likely to become false.",
        "constraints": [
          "Keep dialogue consistent with the officer bible and never make the player speak."
        ],
        "narratorSafe": true,
        "stateRefs": [
          "crew.jaya-kel"
        ],
        "effects": []
      }
    },
    {
      "id": "crew.jaya-kel.relationship",
      "type": "crew.relationship",
      "title": "Jaya Kel relationship pressures",
      "datasetId": "eudora-vale.senior-staff",
      "source": {
        "document": "content/campaigns/eudora-vale/crew/EUDORA_VALE_SENIOR_STAFF_CHARACTER_BIBLE.md",
        "refs": []
      },
      "visibility": "directorOnly",
      "audiences": [
        "crewDirector",
        "missionDirector"
      ],
      "scope": {
        "characters": [
          "jaya-kel"
        ],
        "missions": [
          "prelude-the-captains-chair"
        ],
        "campaigns": [
          "broken-accord"
        ],
        "stardateFrom": 55291.4
      },
      "gates": {
        "playerKnowledge": "highTrust",
        "relationshipMin": null,
        "developmentMin": null,
        "requiresRevealedFactIds": [],
        "blocksUntilFactIds": [],
        "requiresOutcomeIds": []
      },
      "retrieval": {
        "lanes": [
          "crew_relationship",
          "pressure"
        ],
        "keywords": [
          "Jaya Kel",
          "relationship",
          "trust"
        ],
        "priority": "normal"
      },
      "payload": {
        "summary": "ProfessionalConfidence: Credible in role; the player's first independent captaincy has not yet been tested. IntegrityTrust: Begins with Starfleet professional trust and changes through candor, accountability, and treatment of hidden costs. PersonalRapport: Familiar from prior XO service, but transformed by the succession and Rhee's death.",
        "constraints": [
          "Relationship values are hidden; show behavior, not numbers."
        ],
        "narratorSafe": false,
        "stateRefs": [
          "relationships.jaya-kel"
        ],
        "effects": []
      }
    },
    {
      "id": "crew.jaya-kel.development",
      "type": "crew.development",
      "title": "Jaya Kel development hooks",
      "datasetId": "eudora-vale.senior-staff",
      "source": {
        "document": "content/campaigns/eudora-vale/crew/EUDORA_VALE_SENIOR_STAFF_CHARACTER_BIBLE.md",
        "refs": []
      },
      "visibility": "directorOnly",
      "audiences": [
        "crewDirector",
        "missionDirector"
      ],
      "scope": {
        "characters": [
          "jaya-kel"
        ],
        "missions": [
          "prelude-the-captains-chair"
        ],
        "campaigns": [
          "broken-accord"
        ],
        "stardateFrom": 55291.4
      },
      "gates": {
        "playerKnowledge": "crisisDisclosure",
        "relationshipMin": null,
        "developmentMin": null,
        "requiresRevealedFactIds": [],
        "blocksUntilFactIds": [],
        "requiresOutcomeIds": []
      },
      "retrieval": {
        "lanes": [
          "crew_development",
          "bplot"
        ],
        "keywords": [
          "Jaya Kel",
          "development",
          "flight-confidence",
          "grief",
          "delegation",
          "traffic-command"
        ],
        "priority": "normal"
      },
      "payload": {
        "summary": "flight-confidence, grief, delegation, traffic-command | Conditional routes become political chokepoints She may resist delegating shuttle work Orbital demonstrations complicate safe transit",
        "constraints": [
          "Use as Director-only arc material until revealed in play."
        ],
        "narratorSafe": false,
        "stateRefs": [
          "crew.jaya-kel.development"
        ],
        "effects": []
      }
    },
    {
      "id": "crew.venn-talar.profile",
      "type": "crew.profile",
      "title": "Venn Talar service-record profile",
      "datasetId": "eudora-vale.senior-staff",
      "source": {
        "document": "content/campaigns/eudora-vale/crew/EUDORA_VALE_SENIOR_STAFF_CHARACTER_BIBLE.md",
        "refs": []
      },
      "visibility": "publicPackage",
      "audiences": [
        "crewDirector",
        "missionDirector",
        "narrator"
      ],
      "scope": {
        "characters": [
          "venn-talar"
        ],
        "missions": [
          "prelude-the-captains-chair"
        ],
        "campaigns": [
          "broken-accord"
        ],
        "stardateFrom": 55291.4
      },
      "gates": {
        "playerKnowledge": "serviceRecord",
        "relationshipMin": null,
        "developmentMin": null,
        "requiresRevealedFactIds": [],
        "blocksUntilFactIds": [],
        "requiresOutcomeIds": []
      },
      "retrieval": {
        "lanes": [
          "crew_profile",
          "command"
        ],
        "keywords": [
          "Venn Talar",
          "Counselor and Diplomatic Support Officer",
          "Betazoid"
        ],
        "priority": "normal"
      },
      "payload": {
        "summary": "Candid, low-key, and skilled at group process. Talar warns that system consensus often means the most powerful worlds agree with one another.",
        "constraints": [
          "Use as player-safe crew context; do not write for the player."
        ],
        "narratorSafe": true,
        "stateRefs": [
          "crew.venn-talar"
        ],
        "effects": []
      }
    },
    {
      "id": "crew.venn-talar.voice",
      "type": "crew.voice",
      "title": "Venn Talar voice and conduct",
      "datasetId": "eudora-vale.senior-staff",
      "source": {
        "document": "content/campaigns/eudora-vale/crew/EUDORA_VALE_SENIOR_STAFF_CHARACTER_BIBLE.md",
        "refs": []
      },
      "visibility": "playerDiscoverable",
      "audiences": [
        "crewDirector",
        "missionDirector",
        "narrator"
      ],
      "scope": {
        "characters": [
          "venn-talar"
        ],
        "missions": [
          "prelude-the-captains-chair"
        ],
        "campaigns": [
          "broken-accord"
        ],
        "stardateFrom": 55291.4
      },
      "gates": {
        "playerKnowledge": "professionalConversation",
        "relationshipMin": null,
        "developmentMin": null,
        "requiresRevealedFactIds": [],
        "blocksUntilFactIds": [],
        "requiresOutcomeIds": []
      },
      "retrieval": {
        "lanes": [
          "crew_voice",
          "dialogue"
        ],
        "keywords": [
          "Venn Talar",
          "voice",
          "medical"
        ],
        "priority": "normal"
      },
      "payload": {
        "summary": "Plain, patient, and lightly ironic. Talar names emotional facts without claiming telepathic certainty and asks who is absent from the room.",
        "constraints": [
          "Keep dialogue consistent with the officer bible and never make the player speak."
        ],
        "narratorSafe": true,
        "stateRefs": [
          "crew.venn-talar"
        ],
        "effects": []
      }
    },
    {
      "id": "crew.venn-talar.relationship",
      "type": "crew.relationship",
      "title": "Venn Talar relationship pressures",
      "datasetId": "eudora-vale.senior-staff",
      "source": {
        "document": "content/campaigns/eudora-vale/crew/EUDORA_VALE_SENIOR_STAFF_CHARACTER_BIBLE.md",
        "refs": []
      },
      "visibility": "directorOnly",
      "audiences": [
        "crewDirector",
        "missionDirector"
      ],
      "scope": {
        "characters": [
          "venn-talar"
        ],
        "missions": [
          "prelude-the-captains-chair"
        ],
        "campaigns": [
          "broken-accord"
        ],
        "stardateFrom": 55291.4
      },
      "gates": {
        "playerKnowledge": "highTrust",
        "relationshipMin": null,
        "developmentMin": null,
        "requiresRevealedFactIds": [],
        "blocksUntilFactIds": [],
        "requiresOutcomeIds": []
      },
      "retrieval": {
        "lanes": [
          "crew_relationship",
          "pressure"
        ],
        "keywords": [
          "Venn Talar",
          "relationship",
          "trust"
        ],
        "priority": "normal"
      },
      "payload": {
        "summary": "ProfessionalConfidence: Credible in role; the player's first independent captaincy has not yet been tested. IntegrityTrust: Begins with Starfleet professional trust and changes through candor, accountability, and treatment of hidden costs. PersonalRapport: Familiar from prior XO service, but transformed by the succession and Rhee's death.",
        "constraints": [
          "Relationship values are hidden; show behavior, not numbers."
        ],
        "narratorSafe": false,
        "stateRefs": [
          "relationships.venn-talar"
        ],
        "effects": []
      }
    },
    {
      "id": "crew.venn-talar.development",
      "type": "crew.development",
      "title": "Venn Talar development hooks",
      "datasetId": "eudora-vale.senior-staff",
      "source": {
        "document": "content/campaigns/eudora-vale/crew/EUDORA_VALE_SENIOR_STAFF_CHARACTER_BIBLE.md",
        "refs": []
      },
      "visibility": "directorOnly",
      "audiences": [
        "crewDirector",
        "missionDirector"
      ],
      "scope": {
        "characters": [
          "venn-talar"
        ],
        "missions": [
          "prelude-the-captains-chair"
        ],
        "campaigns": [
          "broken-accord"
        ],
        "stardateFrom": 55291.4
      },
      "gates": {
        "playerKnowledge": "crisisDisclosure",
        "relationshipMin": null,
        "developmentMin": null,
        "requiresRevealedFactIds": [],
        "blocksUntilFactIds": [],
        "requiresOutcomeIds": []
      },
      "retrieval": {
        "lanes": [
          "crew_development",
          "bplot"
        ],
        "keywords": [
          "Venn Talar",
          "development",
          "group-process",
          "crew-grief",
          "public-legitimacy",
          "exclusion"
        ],
        "priority": "normal"
      },
      "payload": {
        "summary": "group-process, crew-grief, public-legitimacy, exclusion | Crew needs space for Rhee Summits can become theater Telepathic boundaries matter during high emotion",
        "constraints": [
          "Use as Director-only arc material until revealed in play."
        ],
        "narratorSafe": false,
        "stateRefs": [
          "crew.venn-talar.development"
        ],
        "effects": []
      }
    }
  ],
  "indexes": {
    "byOfficer": {
      "nasrin-rhee": [
        "crew.nasrin-rhee.profile",
        "crew.nasrin-rhee.voice",
        "crew.nasrin-rhee.relationship",
        "crew.nasrin-rhee.development"
      ],
      "asha-ren": [
        "crew.asha-ren.profile",
        "crew.asha-ren.voice",
        "crew.asha-ren.relationship",
        "crew.asha-ren.development"
      ],
      "haro-chveth": [
        "crew.haro-chveth.profile",
        "crew.haro-chveth.voice",
        "crew.haro-chveth.relationship",
        "crew.haro-chveth.development"
      ],
      "milo-fenn": [
        "crew.milo-fenn.profile",
        "crew.milo-fenn.voice",
        "crew.milo-fenn.relationship",
        "crew.milo-fenn.development"
      ],
      "ila-tovan": [
        "crew.ila-tovan.profile",
        "crew.ila-tovan.voice",
        "crew.ila-tovan.relationship",
        "crew.ila-tovan.development"
      ],
      "koris-zhraal": [
        "crew.koris-zhraal.profile",
        "crew.koris-zhraal.voice",
        "crew.koris-zhraal.relationship",
        "crew.koris-zhraal.development"
      ],
      "jaya-kel": [
        "crew.jaya-kel.profile",
        "crew.jaya-kel.voice",
        "crew.jaya-kel.relationship",
        "crew.jaya-kel.development"
      ],
      "venn-talar": [
        "crew.venn-talar.profile",
        "crew.venn-talar.voice",
        "crew.venn-talar.relationship",
        "crew.venn-talar.development"
      ]
    },
    "byType": {
      "crew.profile": [
        "crew.nasrin-rhee.profile",
        "crew.asha-ren.profile",
        "crew.haro-chveth.profile",
        "crew.milo-fenn.profile",
        "crew.ila-tovan.profile",
        "crew.koris-zhraal.profile",
        "crew.jaya-kel.profile",
        "crew.venn-talar.profile"
      ],
      "crew.voice": [
        "crew.nasrin-rhee.voice",
        "crew.asha-ren.voice",
        "crew.haro-chveth.voice",
        "crew.milo-fenn.voice",
        "crew.ila-tovan.voice",
        "crew.koris-zhraal.voice",
        "crew.jaya-kel.voice",
        "crew.venn-talar.voice"
      ],
      "crew.relationship": [
        "crew.nasrin-rhee.relationship",
        "crew.asha-ren.relationship",
        "crew.haro-chveth.relationship",
        "crew.milo-fenn.relationship",
        "crew.ila-tovan.relationship",
        "crew.koris-zhraal.relationship",
        "crew.jaya-kel.relationship",
        "crew.venn-talar.relationship"
      ],
      "crew.development": [
        "crew.nasrin-rhee.development",
        "crew.asha-ren.development",
        "crew.haro-chveth.development",
        "crew.milo-fenn.development",
        "crew.ila-tovan.development",
        "crew.koris-zhraal.development",
        "crew.jaya-kel.development",
        "crew.venn-talar.development"
      ]
    },
    "byAudience": {
      "crewDirector": [
        "crew.nasrin-rhee.profile",
        "crew.nasrin-rhee.voice",
        "crew.nasrin-rhee.relationship",
        "crew.nasrin-rhee.development",
        "crew.asha-ren.profile",
        "crew.asha-ren.voice",
        "crew.asha-ren.relationship",
        "crew.asha-ren.development",
        "crew.haro-chveth.profile",
        "crew.haro-chveth.voice",
        "crew.haro-chveth.relationship",
        "crew.haro-chveth.development",
        "crew.milo-fenn.profile",
        "crew.milo-fenn.voice",
        "crew.milo-fenn.relationship",
        "crew.milo-fenn.development",
        "crew.ila-tovan.profile",
        "crew.ila-tovan.voice",
        "crew.ila-tovan.relationship",
        "crew.ila-tovan.development",
        "crew.koris-zhraal.profile",
        "crew.koris-zhraal.voice",
        "crew.koris-zhraal.relationship",
        "crew.koris-zhraal.development",
        "crew.jaya-kel.profile",
        "crew.jaya-kel.voice",
        "crew.jaya-kel.relationship",
        "crew.jaya-kel.development",
        "crew.venn-talar.profile",
        "crew.venn-talar.voice",
        "crew.venn-talar.relationship",
        "crew.venn-talar.development"
      ],
      "missionDirector": [
        "crew.nasrin-rhee.profile",
        "crew.nasrin-rhee.voice",
        "crew.nasrin-rhee.relationship",
        "crew.nasrin-rhee.development",
        "crew.asha-ren.profile",
        "crew.asha-ren.voice",
        "crew.asha-ren.relationship",
        "crew.asha-ren.development",
        "crew.haro-chveth.profile",
        "crew.haro-chveth.voice",
        "crew.haro-chveth.relationship",
        "crew.haro-chveth.development",
        "crew.milo-fenn.profile",
        "crew.milo-fenn.voice",
        "crew.milo-fenn.relationship",
        "crew.milo-fenn.development",
        "crew.ila-tovan.profile",
        "crew.ila-tovan.voice",
        "crew.ila-tovan.relationship",
        "crew.ila-tovan.development",
        "crew.koris-zhraal.profile",
        "crew.koris-zhraal.voice",
        "crew.koris-zhraal.relationship",
        "crew.koris-zhraal.development",
        "crew.jaya-kel.profile",
        "crew.jaya-kel.voice",
        "crew.jaya-kel.relationship",
        "crew.jaya-kel.development",
        "crew.venn-talar.profile",
        "crew.venn-talar.voice",
        "crew.venn-talar.relationship",
        "crew.venn-talar.development"
      ],
      "narrator": [
        "crew.nasrin-rhee.profile",
        "crew.nasrin-rhee.voice",
        "crew.asha-ren.profile",
        "crew.asha-ren.voice",
        "crew.haro-chveth.profile",
        "crew.haro-chveth.voice",
        "crew.milo-fenn.profile",
        "crew.milo-fenn.voice",
        "crew.ila-tovan.profile",
        "crew.ila-tovan.voice",
        "crew.koris-zhraal.profile",
        "crew.koris-zhraal.voice",
        "crew.jaya-kel.profile",
        "crew.jaya-kel.voice",
        "crew.venn-talar.profile",
        "crew.venn-talar.voice"
      ]
    },
    "byRevealGate": {
      "serviceRecord": [
        "crew.nasrin-rhee.profile",
        "crew.asha-ren.profile",
        "crew.haro-chveth.profile",
        "crew.milo-fenn.profile",
        "crew.ila-tovan.profile",
        "crew.koris-zhraal.profile",
        "crew.jaya-kel.profile",
        "crew.venn-talar.profile"
      ],
      "professionalConversation": [
        "crew.nasrin-rhee.voice",
        "crew.asha-ren.voice",
        "crew.haro-chveth.voice",
        "crew.milo-fenn.voice",
        "crew.ila-tovan.voice",
        "crew.koris-zhraal.voice",
        "crew.jaya-kel.voice",
        "crew.venn-talar.voice"
      ],
      "highTrust": [
        "crew.nasrin-rhee.relationship",
        "crew.asha-ren.relationship",
        "crew.haro-chveth.relationship",
        "crew.milo-fenn.relationship",
        "crew.ila-tovan.relationship",
        "crew.koris-zhraal.relationship",
        "crew.jaya-kel.relationship",
        "crew.venn-talar.relationship"
      ],
      "crisisDisclosure": [
        "crew.nasrin-rhee.development",
        "crew.asha-ren.development",
        "crew.haro-chveth.development",
        "crew.milo-fenn.development",
        "crew.ila-tovan.development",
        "crew.koris-zhraal.development",
        "crew.jaya-kel.development",
        "crew.venn-talar.development"
      ]
    }
  }
}
